MANIFEST.in
README.rst
setup.py
sockjs/__init__.py
sockjs/tornado/__init__.py
sockjs/tornado/basehandler.py
sockjs/tornado/conn.py
sockjs/tornado/migrate.py
sockjs/tornado/periodic.py
sockjs/tornado/proto.py
sockjs/tornado/router.py
sockjs/tornado/session.py
sockjs/tornado/sessioncontainer.py
sockjs/tornado/static.py
sockjs/tornado/stats.py
sockjs/tornado/util.py
sockjs/tornado/websocket.py
sockjs/tornado/transports/__init__.py
sockjs/tornado/transports/base.py
sockjs/tornado/transports/eventsource.py
sockjs/tornado/transports/htmlfile.py
sockjs/tornado/transports/jsonp.py
sockjs/tornado/transports/pollingbase.py
sockjs/tornado/transports/rawwebsocket.py
sockjs/tornado/transports/streamingbase.py
sockjs/tornado/transports/websocket.py
sockjs/tornado/transports/xhr.py
sockjs/tornado/transports/xhrstreaming.py
sockjs_tornado.egg-info/PKG-INFO
sockjs_tornado.egg-info/SOURCES.txt
sockjs_tornado.egg-info/dependency_links.txt
sockjs_tornado.egg-info/namespace_packages.txt
sockjs_tornado.egg-info/requires.txt
sockjs_tornado.egg-info/top_level.txt