Metadata-Version: 1.1
Name: sockjs-tornado
Version: 1.0.0
Summary: SockJS python server implementation on top of Tornado framework
Home-page: http://github.com/mrjoes/sockjs-tornado/
Author: Serge S. Koval
Author-email: serge.koval@gmail.com
License: Copyright (C) 2011 Serge S. Koval
